astro3words/__init__.py
astro3words/astro3words.py
tests/__init__.py
tests/test_astro3words.py
astro3words-0.3.3.dist-info/LICENSE
astro3words-0.3.3.dist-info/METADATA
astro3words-0.3.3.dist-info/WHEEL
astro3words-0.3.3.dist-info/top_level.txt
astro3words-0.3.3.dist-info/RECORD
