Metadata-Version: 2.1
Name: astro3words
Version: 0.3.3
Summary: astro3words - get a simple 3-word coordinate of your favorite object!
Home-page: https://github.com/astro-nova/astro-3-words
Author: UNKNOWN
Author-email: UNKNOWN
License: MIT
Keywords: Astronomy Astrometry
Platform: UNKNOWN
Classifier: Intended Audience :: Science/Research
Classifier: Topic :: Scientific/Engineering :: Astronomy
Classifier: Programming Language :: Python :: 3
Requires-Dist: what3words
Requires-Dist: astropy
Requires-Dist: numpy
Requires-Dist: sphinx
Requires-Dist: ipykernel
Requires-Dist: nbsphinx
Requires-Dist: pytest
